subtitle_editor/__init__.py
subtitle_editor/__version__.py
subtitle_editor/cli.py
subtitle_editor/colors.py
subtitle_editor/constants.py
subtitle_editor/video.py
subtitle_editor/subtitles/__init__.py
subtitle_editor/subtitles/srt.py
test/__init__.py
test/conftest.py
test/factories.py
test/subtitles/__init__.py
subtitle_editor-0.3.0.dist-info/LICENSE
subtitle_editor-0.3.0.dist-info/METADATA
subtitle_editor-0.3.0.dist-info/WHEEL
subtitle_editor-0.3.0.dist-info/entry_points.txt
subtitle_editor-0.3.0.dist-info/top_level.txt
subtitle_editor-0.3.0.dist-info/RECORD
