Metadata-Version: 2.1
Name: subtitle-editor
Version: 0.3.0
Summary: Edit subtitles in your terminal instead of a text editor.
Home-page: https://github.com/sandalwoodbox/subtitle-editor
Author: sandalwoodbox
Author-email: boxofsandalwood@gmail.com
License: GPL version 3
Platform: UNKNOWN
Classifier: License :: OSI Approved :: GNU General Public License v3 (GPLv3)
Classifier: Programming Language :: Python
Classifier: Programming Language :: Python :: 3
Classifier: Programming Language :: Python :: 3.7
Classifier: Programming Language :: Python :: Implementation :: CPython
Classifier: Topic :: Multimedia :: Video
Requires-Python: >=3.7.0
Requires-Dist: click
Requires-Dist: ffmpeg-python
Requires-Dist: opencv-python
Requires-Dist: pyaudio
Requires-Dist: srt
